{
    "1": "⠡",
    "2": "⠣",
    "3": "⠩",
    "4": "⠹",
    "5": "⠱",
    "6": "⠫",
    "7": "⠻",
    "8": "⠳",
    "b": "⠃",
    "p": "⠏",
    "m": "⠍",
    "w": "⠺",
    "j": "⠚",
    "q": "⠟",
    "x": "⠭",
    "y": "⠽",
    "n": "⠝",
    "z": "⠵",
    "D": "⠲",
    "s": "⠎",
    "r": "⠗",
    "H": "⠦",
    "N": "⠜",
    "l": "⠇",
    "d": "⠙",
    "t": "⠞",
    "g": "⠛",
    "k": "⠅",
    "h": "⠓",
    "v": "⠧",
    "F": "⠖",
    "B": "⠆",
    "c": "⠉",
    "f": "⠋",
    "u": "⠥",
    "a": "⠁",
    "o": "⠕",
    "e": "⠑",
    "E": "⠬",
    "A": "⠷",
    "Y": "⠤",
    "L": "⠿",
    "T": "⠪",
    "V": "⠯",
    "i": "⠊",
    ".": "⠐⠐",
    ",": "⠐",
    ";": "⠐⠰",
    "?": "⠐⠄",
    "!": "⠐⠒",
    ":": "⠐⠤",
    "·": "⠠",
    "⟡": "⠠⠄",
    "⟦": "⠠⠃",
    "⟧": "⠘⠄",
    "“": "⠘",
    "”": "⠘",
    "‘": "⠘⠘",
    "’": "⠘⠘",
    "(": "⠠⠆",
    ")": "⠰⠄",
    "«": "⠠⠇",
    "»": "⠸⠄",
    "‹": "⠠⠇",
    "›": "⠸⠄",
    "…": "⠐⠐⠐",
    "—": "⠐⠒⠒"
}